{
  "Parameters": {
    "rm1_l": 0.23,
    "rm1_w": 0.23,
    "rm2_3_l": 0.28,
    "rm2_3_w": 0.28,
    "tm6k_l": 0.36,
    "tm6k_w": 0.36,
    "tm9_11k_l": 0.44,
    "tm9_11k_w": 0.44,
    "tm30k_l": 1.8,
    "tm30k_w": 1.8,
    "nplus_s_l": 0.42,
    "nplus_s_w": 0.42,
    "pplus_s_l": 0.42,
    "pplus_s_w": 0.42,
    "nplus_u_l": 0.42,
    "nplus_u_w": 0.42,
    "pplus_u_l": 0.42,
    "pplus_u_w": 0.42,
    "nwell_l": 0.42,
    "nwell_w": 0.42,
    "pwell_l": 0.42,
    "pwell_w": 0.42,
    "npolyf_s_l": 0.42,
    "npolyf_s_w": 0.42,
    "ppolyf_s_l": 0.42,
    "ppolyf_s_w": 0.42,
    "npolyf_u_l": 0.42,
    "npolyf_u_w": 0.42,
    "ppolyf_u_l": 0.42,
    "ppolyf_u_w": 0.42,
    "ppolyf_u_h_res_l": 0.42,
    "ppolyf_u_h_res_w": 0.42
  },
  "Layers": {
    "layer1.drawing": "1, 222",
    "pass.marker": "2, 222",
    "fail.marker": "3, 222",
    "polygon.marker": "4, 222",
    "pass_mk.marker": "2, 222",
    "fail_mk.marker": "3, 222",
    "polygon_mk.marker": "4, 222",
    "layer5.drawing": "5, 222",
    "violation.marker": "6, 222",
    "rule_txt.marker": "11, 222",
    "violation_mk.marker": "6, 222",
    "rule_txt_mk.marker": "11, 222",
    "layer12.drawing": "12, 222",
    "case_txt.marker": "13, 222",
    "case_txt_mk.marker": "13, 222",
    "layer14.drawing": "14, 222",
    "layer15.drawing": "15, 222",
    "COMP.drawing": "22, 0",
    "DNWELL.drawing": "12, 0",
    "Nwell.drawing": "21, 0",
    "LVPWELL.drawing": "204, 0",
    "Dualgate.drawing": "55, 0",
    "Poly2.drawing": "30, 0",
    "Nplus.drawing": "32, 0",
    "Pplus.drawing": "31, 0",
    "SAB.drawing": "49, 0",
    "ESD.drawing": "24, 0",
    "Contact.drawing": "33, 0",
    "Metal1.drawing": "34, 0",
    "Via1.drawing": "35, 0",
    "Metal2.drawing": "36, 0",
    "Via2.drawing": "38, 0",
    "Metal3.drawing": "42, 0",
    "Via3.drawing": "40, 0",
    "Metal4.drawing": "46, 0",
    "Via4.drawing": "41, 0",
    "Metal5.drawing": "81, 0",
    "Via5.drawing": "82, 0",
    "MetalTop.drawing": "53, 0",
    "Pad.drawing": "37, 0",
    "Resistor.drawing": "62, 0",
    "FHRES.drawing": "227, 0",
    "FuseTop.drawing": "75, 0",
    "FuseWindow_D.drawing": "96, 1",
    "POLYFUSE.drawing": "220, 0",
    "MVSD.drawing": "210, 0",
    "MVPSD.drawing": "11, 39",
    "NAT.drawing": "5, 0",
    "COMP.dummy": "22, 4",
    "Poly2.dummy": "30, 4",
    "Metal1.dummy": "34, 4",
    "Metal2.dummy": "36, 4",
    "Metal3.dummy": "42, 4",
    "Metal4.dummy": "46, 4",
    "Metal5.dummy": "81, 4",
    "MetalTop.dummy": "53, 4",
    "COMP.label": "22, 10",
    "Poly2.label": "30, 10",
    "Metal1.label": "34, 10",
    "Metal2.label": "36, 10",
    "Metal3.label": "42, 10",
    "Metal4.label": "46, 10",
    "Metal5.label": "81, 10",
    "MetalTop.label": "53, 10",
    "Metal1.slot": "34, 3",
    "Metal2.slot": "36, 3",
    "Metal3.slot": "42, 3",
    "Metal4.slot": "46, 3",
    "Metal5.slot": "81, 3",
    "MetalTop.slot": "53, 3",
    "COMP_Dummy.dummy": "22, 4",
    "Poly2_Dummy.dummy": "30, 4",
    "Metal1_Dummy.dummy": "34, 4",
    "Metal2_Dummy.dummy": "36, 4",
    "Metal3_Dummy.dummy": "42, 4",
    "Metal4_Dummy.dummy": "46, 4",
    "Metal5_Dummy.dummy": "81, 4",
    "MetalTop_Dummy.dummy": "53, 4",
    "COMP_Label.label": "22, 10",
    "Poly2_Label.label": "30, 10",
    "Metal1_Label.label": "34, 10",
    "Metal2_Label.label": "36, 10",
    "Metal3_Label.label": "42, 10",
    "Metal4_Label.label": "46, 10",
    "Metal5_Label.label": "81, 10",
    "MetalTop_Label.label": "53, 10",
    "Metal1_Slot.slot": "34, 3",
    "Metal2_Slot.slot": "36, 3",
    "Metal3_Slot.slot": "42, 3",
    "Metal4_Slot.slot": "46, 3",
    "Metal5_Slot.slot": "81, 3",
    "MetalTop_Slot.slot": "53, 3",
    "UBMPPeri.drawing": "183, 0",
    "UBMPArray.drawing": "184, 0",
    "UBMEPlate.drawing": "185, 0",
    "Schottky_diode.drawing": "241, 0",
    "ZENER.drawing": "178, 0",
    "RES.marker": "110, 5",
    "OPC_drc.drawing": "124, 5",
    "NDMY.drawing": "111, 5",
    "PMNDMY.drawing": "152, 5",
    "V5_XTOR.drawing": "112, 1",
    "CAP.marker": "117, 5",
    "MOS_CAP.marker": "166, 5",
    "IND.marker": "151, 5",
    "DIODE.marker": "115, 5",
    "CAP_MK.marker": "117, 5",
    "MOS_CAP_MK.marker": "166, 5",
    "IND_MK.marker": "151, 5",
    "DIODE_MK.marker": "115, 5",
    "DRC_BJT.drawing": "127, 5",
    "LVS_BJT.drawing": "118, 5",
    "MIM_L.marker": "117, 10",
    "Latchup.marker": "137, 5",
    "GUARD_RING.marker": "167, 5",
    "OTP.marker": "173, 5",
    "MIM_L_MK.marker": "117, 10",
    "Latchup_MK.marker": "137, 5",
    "GUARD_RING_MK.marker": "167, 5",
    "OTP_MK.marker": "173, 5",
    "MTPMARK.drawing": "122, 5",
    "NEO_EE.marker": "88, 17",
    "NEO_EE_MK.marker": "88, 17",
    "SramCore.drawing": "108, 5",
    "LVS_RF.drawing": "100, 5",
    "LVS_Drain.drawing": "100, 7",
    "HVPOLYRS.drawing": "123, 5",
    "LVS_IO.drawing": "119, 5",
    "PROBE.marker": "13, 17",
    "ESD.marker": "24, 5",
    "PROBE_MK.marker": "13, 17",
    "ESD_MK.marker": "24, 5",
    "LVS_Source.drawing": "100, 8",
    "WELL_DIODE.marker": "153, 51",
    "WELL_DIODE_MK.marker": "153, 51",
    "LDMOS_XTOR.drawing": "226, 0",
    "PLFUSE.drawing": "125, 5",
    "EFUSE.marker": "80, 5",
    "MCELL_FEOL.marker": "11, 17",
    "YMTP.marker": "86, 17",
    "DEV_WF.marker": "128, 17",
    "Metal1.BLK": "34, 5",
    "Metal2.BLK": "36, 5",
    "Metal3.BLK": "42, 5",
    "Metal4.BLK": "46, 5",
    "Metal5.BLK": "81, 5",
    "MetalT.BLK": "53, 5",
    "EFUSE_MK.marker": "80, 5",
    "MCELL_FEOL_MK.marker": "11, 17",
    "YMTP_MK.marker": "86, 17",
    "DEV_WF_MK.marker": "128, 17",
    "Metal1_BLK.block": "34, 5",
    "Metal2_BLK.block": "36, 5",
    "Metal3_BLK.block": "42, 5",
    "Metal4_BLK.block": "46, 5",
    "Metal5_BLK.block": "81, 5",
    "MetalT_BLK.block": "53, 5",
    "PR_bndry.drawing": "0, 0",
    "MDIODE.drawing": "116, 5",
    "Metal1.res": "110, 11",
    "Metal2.res": "110, 12",
    "Metal3.res": "110, 13",
    "Metal4.res": "110, 14",
    "Metal5.res": "110, 15",
    "Metal6.res": "110, 16",
    "Metal1_Res.drawing": "110, 11",
    "Metal2_Res.drawing": "110, 12",
    "Metal3_Res.drawing": "110, 13",
    "Metal4_Res.drawing": "110, 14",
    "Metal5_Res.drawing": "110, 15",
    "Metal6_Res.drawing": "110, 16",
    "Border.drawing": "63, 0",
    "layer58.drawing": "58, 0",
    "layer63.drawing": "63, 63"
  }
}
